blazeutils/__init__.py
blazeutils/config.py
blazeutils/containers.py
blazeutils/datastructures.py
blazeutils/dates.py
blazeutils/decorators.py
blazeutils/error_handling.py
blazeutils/filesystem.py
blazeutils/functional.py
blazeutils/helpers.py
blazeutils/importing.py
blazeutils/jsonh.py
blazeutils/log.py
blazeutils/numbers.py
blazeutils/rst.py
blazeutils/sentinels.py
blazeutils/spreadsheets.py
blazeutils/strings.py
blazeutils/testing.py
blazeutils/version.py
BlazeUtils-0.7.0.dist-info/METADATA
BlazeUtils-0.7.0.dist-info/WHEEL
BlazeUtils-0.7.0.dist-info/top_level.txt
BlazeUtils-0.7.0.dist-info/RECORD
