Metadata-Version: 2.1
Name: BlazeUtils
Version: 0.7.0
Summary: A collection of python utility functions and classes.
Home-page: https://github.com/blazelibs/blazeutils/
Author: Randy Syring
Author-email: randy.syring@level12.io
License: BSD
Platform: UNKNOWN
Classifier: Development Status :: 4 - Beta
Classifier: Intended Audience :: Developers
Classifier: License :: OSI Approved :: BSD License
Classifier: Operating System :: OS Independent
Classifier: Programming Language :: Python :: 3
Classifier: Programming Language :: Python :: 3.7
Classifier: Programming Language :: Python :: 3.8
Classifier: Programming Language :: Python :: 3.9
Classifier: Programming Language :: Python :: 3.10
Requires-Python: >=3
Requires-Dist: wrapt
Provides-Extra: dev
Requires-Dist: codecov ; extra == 'dev'
Requires-Dist: docutils ; extra == 'dev'
Requires-Dist: openpyxl ; extra == 'dev'
Requires-Dist: pytest ; extra == 'dev'
Requires-Dist: pytest-cov ; extra == 'dev'
Requires-Dist: sqlalchemy ; extra == 'dev'
Requires-Dist: tox ; extra == 'dev'
Requires-Dist: wheel ; extra == 'dev'
Requires-Dist: xlwt ; extra == 'dev'
Requires-Dist: xlrd (<2.0.0) ; extra == 'dev'
Requires-Dist: xlsxwriter ; extra == 'dev'
Requires-Dist: colorama ; extra == 'dev'
Requires-Dist: flake8 ; extra == 'dev'
Requires-Dist: restview ; extra == 'dev'
Provides-Extra: test
Requires-Dist: codecov ; extra == 'test'
Requires-Dist: docutils ; extra == 'test'
Requires-Dist: openpyxl ; extra == 'test'
Requires-Dist: pytest ; extra == 'test'
Requires-Dist: pytest-cov ; extra == 'test'
Requires-Dist: sqlalchemy ; extra == 'test'
Requires-Dist: tox ; extra == 'test'
Requires-Dist: wheel ; extra == 'test'
Requires-Dist: xlwt ; extra == 'test'
Requires-Dist: xlrd (<2.0.0) ; extra == 'test'
Requires-Dist: xlsxwriter ; extra == 'test'
Requires-Dist: colorama ; extra == 'test'
